{"stat.craftItem.minecraft.furnace":1,"stat.walkOneCm":59743,"stat.craftItem.minecraft.bed":1,"stat.useItem.minecraft.bed":1,"achievement.openInventory":6,"stat.craftItem.minecraft.planks":40,"stat.craftItem.minecraft.stone_axe":1,"stat.leaveGame":1,"stat.mineBlock.minecraft.vine":9,"stat.useItem.minecraft.log":1,"stat.damageTaken":40,"stat.mineBlock.minecraft.crafting_table":1,"stat.craftItem.minecraft.crafting_table":1,"stat.furnaceInteraction":3,"stat.useItem.minecraft.wooden_pickaxe":19,"stat.useItem.minecraft.furnace":1,"stat.mobKills":3,"stat.useItem.minecraft.dye":1,"stat.mineBlock.minecraft.log":19,"stat.flyOneCm":15786,"stat.jump":204,"stat.mineBlock.minecraft.leaves":1,"stat.swimOneCm":2031,"stat.playOneMinute":17770,"stat.fallOneCm":2732,"stat.climbOneCm":828,"stat.useItem.minecraft.planks":26,"stat.killEntity.Sheep":3,"stat.useItem.minecraft.cooked_mutton":3,"stat.useItem.minecraft.stone_axe":2,"stat.damageDealt":205,"stat.crouchOneCm":1130,"stat.timeSinceDeath":17770,"achievement.mineWood":1,"stat.useItem.minecraft.dirt":4,"stat.sprintOneCm":14670,"stat.useItem.minecraft.crafting_table":2,"stat.mineBlock.minecraft.dirt":7,"stat.craftItem.minecraft.wooden_pickaxe":1,"stat.mineBlock.minecraft.stone":19,"achievement.exploreAllBiomes":{"value":0,"progress":["Jungle","River","JungleEdge","Savanna"]},"stat.mineBlock.minecraft.tallgrass":27,"stat.craftItem.minecraft.cooked_mutton":3,"stat.craftItem.minecraft.stick":4,"stat.craftingTableInteraction":3}